cflabs_serverless/__init__.py
cflabs_serverless/cli.py
cflabs_serverless/templates.py
cflabs_serverless/utils.py
cflabs_serverless-0.3.3.dist-info/METADATA
cflabs_serverless-0.3.3.dist-info/WHEEL
cflabs_serverless-0.3.3.dist-info/entry_points.txt
cflabs_serverless-0.3.3.dist-info/licenses/LICENSE
cflabs_serverless-0.3.3.dist-info/RECORD
