Metadata-Version: 2.4
Name: cflabs-serverless
Version: 0.3.3
Summary: Deploy Flask apps to AWS Lambda + API Gateway with zero code changes
Project-URL: Homepage, https://github.com/cosmicfusionlabs/cflabs-serverless
Project-URL: Repository, https://github.com/cosmicfusionlabs/cflabs-serverless
Project-URL: Issues, https://github.com/cosmicfusionlabs/cflabs-serverless/issues
Author-email: CosmicFusionLabs <info@cosmicfusionlabs.com>
License: MIT
License-File: LICENSE
Classifier: Development Status :: 3 - Alpha
Classifier: Intended Audience :: Developers
Classifier: License :: OSI Approved :: MIT License
Classifier: Programming Language :: Python :: 3
Classifier: Programming Language :: Python :: 3.8
Classifier: Programming Language :: Python :: 3.9
Classifier: Programming Language :: Python :: 3.10
Classifier: Programming Language :: Python :: 3.11
Classifier: Programming Language :: Python :: 3.12
Classifier: Topic :: Internet :: WWW/HTTP :: WSGI :: Application
Classifier: Topic :: Software Development :: Libraries :: Python Modules
Requires-Python: >=3.8
Requires-Dist: boto3>=1.26.0
Requires-Dist: docker>=6.0.0
Requires-Dist: jinja2>=3.1.0
Requires-Dist: pyyaml>=6.0.0
Requires-Dist: rich>=13.0.0
Requires-Dist: typer>=0.9.0
Provides-Extra: dev
Requires-Dist: black>=23.0.0; extra == 'dev'
Requires-Dist: flake8>=6.0.0; extra == 'dev'
Requires-Dist: isort>=5.12.0; extra == 'dev'
Requires-Dist: mypy>=1.0.0; extra == 'dev'
Requires-Dist: pytest-cov>=4.0.0; extra == 'dev'
Requires-Dist: pytest>=7.0.0; extra == 'dev'
